propulate/__init__.py
propulate/_globals.py
propulate/islands.py
propulate/migrator.py
propulate/pollinator.py
propulate/population.py
propulate/propulator.py
propulate/surrogate.py
propulate/propagators/__init__.py
propulate/propagators/base.py
propulate/propagators/cmaes.py
propulate/propagators/ga.py
propulate/propagators/nm.py
propulate/propagators/pso.py
propulate/utils/__init__.py
propulate/utils/benchmark_functions.py
propulate-1.2.2.dist-info/AUTHORS.md
propulate-1.2.2.dist-info/LICENSE.md
propulate-1.2.2.dist-info/METADATA
propulate-1.2.2.dist-info/WHEEL
propulate-1.2.2.dist-info/top_level.txt
propulate-1.2.2.dist-info/RECORD
