Metadata-Version: 2.1
Name: propulate
Version: 1.2.2
Summary: Massively parallel genetic optimization through asynchronous propagation of populations
Author-email: "Marie Weiel, Oskar Taubert, Helmholtz AI" <propulate@lists.kit.edu>
Project-URL: Homepage, https://github.com/Helmholtz-AI-Energy/propulate
Project-URL: Issues, https://github.com/Helmholtz-AI-Energy/propulate/issues
Classifier: Programming Language :: Python :: 3
Classifier: License :: OSI Approved :: BSD License
Classifier: Development Status :: 3 - Alpha
Requires-Python: >=3.9
License-File: LICENSE.md
License-File: AUTHORS.md
Requires-Dist: deepdiff
Requires-Dist: matplotlib ~=3.8.4
Requires-Dist: mpi4py
Requires-Dist: numpy
Requires-Dist: colorlog
Requires-Dist: Gpy ~=1.13.1
Requires-Dist: h5py
Provides-Extra: dev
Requires-Dist: pre-commit ; extra == 'dev'
Requires-Dist: coverage ; extra == 'dev'
Requires-Dist: ruff ; extra == 'dev'
Requires-Dist: mypy ; extra == 'dev'
Requires-Dist: pytest ; extra == 'dev'
Requires-Dist: pytest-cov ; extra == 'dev'
Requires-Dist: pytest-mpi ; extra == 'dev'
Requires-Dist: sphinx-autoapi ; extra == 'dev'
Requires-Dist: sphinx-rtd-theme ; extra == 'dev'
Requires-Dist: sphinxcontrib-napoleon ; extra == 'dev'
Requires-Dist: sphinxemoji ; extra == 'dev'
Requires-Dist: torch ; extra == 'dev'
Requires-Dist: torchvision ; extra == 'dev'
Requires-Dist: torchmetrics ; extra == 'dev'
Provides-Extra: tutorials
Requires-Dist: torch ; extra == 'tutorials'
Requires-Dist: torchvision ; extra == 'tutorials'
Requires-Dist: torchmetrics ; extra == 'tutorials'
Requires-Dist: lightning ; extra == 'tutorials'
